drivefs_sleuth/__init__.py
drivefs_sleuth/executor.py
drivefs_sleuth/setup.py
drivefs_sleuth/synced_files_tree.py
drivefs_sleuth/tasks.py
drivefs_sleuth/utils.py
drivefs_sleuth/html_resources/report_template.html
drivefs_sleuth-1.2.1.dist-info/LICENSE
drivefs_sleuth-1.2.1.dist-info/METADATA
drivefs_sleuth-1.2.1.dist-info/WHEEL
drivefs_sleuth-1.2.1.dist-info/entry_points.txt
drivefs_sleuth-1.2.1.dist-info/top_level.txt
drivefs_sleuth-1.2.1.dist-info/RECORD
