Metadata-Version: 2.1
Name: drivefs_sleuth
Version: 1.2.1
Summary: The ultimate Google Drive File Stream Investigator!
Home-page: https://github.com/AmgdGocha/DriveFS-Sleuth
Author: Amged Wageh
Author-email: amged_wageh@outlook.com
License: Eclipse Public License 2.0
Classifier: Development Status :: 5 - Production/Stable
Classifier: Intended Audience :: Science/Research
Classifier: Intended Audience :: Other Audience
Classifier: License :: OSI Approved :: Eclipse Public License 2.0 (EPL-2.0)
Classifier: Programming Language :: Python :: 3 :: Only
Classifier: Topic :: Scientific/Engineering
Classifier: Topic :: Scientific/Engineering :: Information Analysis
Classifier: Topic :: Security
Classifier: Operating System :: OS Independent
License-File: LICENSE
Requires-Dist: Jinja2~=3.1.2
Requires-Dist: bbpb
